pgtty/PgTTY.py
pgtty/__init__.py
pgtty/font.ttf
pgtty-0.2.1.dist-info/LICENSE
pgtty-0.2.1.dist-info/METADATA
pgtty-0.2.1.dist-info/WHEEL
pgtty-0.2.1.dist-info/top_level.txt
pgtty-0.2.1.dist-info/RECORD
