Metadata-Version: 2.1
Name: pgtty
Version: 0.2.1
Summary: Basic terminal written in pygame
Author-email: Baguette Yeeter <baguetteyeeter@gmail.com>
Project-URL: Homepage, https://github.com/baguetteyeeter/pgtty
Project-URL: Bug Tracker, https://github.com/baguetteyeeter/pgtty/issues
Classifier: Programming Language :: Python :: 3
Requires-Python: >=3.7
License-File: LICENSE
Requires-Dist: pygame
